viterbo/__init__.py
viterbo/cli.py
viterbo/core/__init__.py
viterbo/core/collector.py
viterbo/core/docstring.py
viterbo/core/formatter.py
viterbo/core/utils.py
viterbo/parsers/__init__.py
viterbo/parsers/cpp_parser.py
viterbo/parsers/generic_parser.py
viterbo/parsers/python_parser.py
viterbo/parsers/r_parser.py
viterbo-0.3.5.dist-info/LICENSE
viterbo-0.3.5.dist-info/METADATA
viterbo-0.3.5.dist-info/WHEEL
viterbo-0.3.5.dist-info/entry_points.txt
viterbo-0.3.5.dist-info/RECORD
