Metadata-Version: 2.1
Name: viterbo
Version: 0.3.5
Summary: A tool for collecting and documenting code for LLM context
Author: Francisco Boerr
Author-email: francisco.boerr@deinnovatie.com
Requires-Python: >=3.9,<3.14
Classifier: Programming Language :: Python :: 3
Classifier: Programming Language :: Python :: 3.9
Classifier: Programming Language :: Python :: 3.10
Classifier: Programming Language :: Python :: 3.11
Classifier: Programming Language :: Python :: 3.12
Requires-Dist: pyperclip (>=1.9.0,<2.0.0)
Project-URL: Logo, https://raw.githubusercontent.com/pboerr/viterbo/main/assets/logo.png
